{
  "url": "https://api.github.com/repos/bolt-design-system/bolt/issues/97",
  "repository_url": "https://api.github.com/repos/bolt-design-system/bolt",
  "labels_url": "https://api.github.com/repos/bolt-design-system/bolt/issues/97/labels{/name}",
  "comments_url": "https://api.github.com/repos/bolt-design-system/bolt/issues/97/comments",
  "events_url": "https://api.github.com/repos/bolt-design-system/bolt/issues/97/events",
  "html_url": "https://github.com/bolt-design-system/bolt/pull/97",
  "id": 250039223,
  "number": 97,
  "title": "Create ITCSS vs Atomic Design.md",
  "user": {
    "login": "sghoweri",
    "id": 1617209,
    "avatar_url": "https://avatars2.githubusercontent.com/u/1617209?v=4",
    "gravatar_id": "",
    "url": "https://api.github.com/users/sghoweri",
    "html_url": "https://github.com/sghoweri",
    "followers_url": "https://api.github.com/users/sghoweri/followers",
    "following_url": "https://api.github.com/users/sghoweri/following{/other_user}",
    "gists_url": "https://api.github.com/users/sghoweri/gists{/gist_id}",
    "starred_url": "https://api.github.com/users/sghoweri/starred{/owner}{/repo}",
    "subscriptions_url": "https://api.github.com/users/sghoweri/subscriptions",
    "organizations_url": "https://api.github.com/users/sghoweri/orgs",
    "repos_url": "https://api.github.com/users/sghoweri/repos",
    "events_url": "https://api.github.com/users/sghoweri/events{/privacy}",
    "received_events_url": "https://api.github.com/users/sghoweri/received_events",
    "type": "User",
    "site_admin": false
  },
  "labels": [],
  "state": "closed",
  "locked": false,
  "assignee": null,
  "assignees": [],
  "milestone": null,
  "comments": 7,
  "created_at": "2017-08-14T13:59:08Z",
  "updated_at": "2017-08-22T12:25:39Z",
  "closed_at": "2017-08-22T12:25:24Z",
  "author_association": "OWNER",
  "pull_request": {
    "url": "https://api.github.com/repos/bolt-design-system/bolt/pulls/97",
    "html_url": "https://github.com/bolt-design-system/bolt/pull/97",
    "diff_url": "https://github.com/bolt-design-system/bolt/pull/97.diff",
    "patch_url": "https://github.com/bolt-design-system/bolt/pull/97.patch"
  },
  "body": "",
  "closed_by": {
    "login": "sghoweri",
    "id": 1617209,
    "avatar_url": "https://avatars2.githubusercontent.com/u/1617209?v=4",
    "gravatar_id": "",
    "url": "https://api.github.com/users/sghoweri",
    "html_url": "https://github.com/sghoweri",
    "followers_url": "https://api.github.com/users/sghoweri/followers",
    "following_url": "https://api.github.com/users/sghoweri/following{/other_user}",
    "gists_url": "https://api.github.com/users/sghoweri/gists{/gist_id}",
    "starred_url": "https://api.github.com/users/sghoweri/starred{/owner}{/repo}",
    "subscriptions_url": "https://api.github.com/users/sghoweri/subscriptions",
    "organizations_url": "https://api.github.com/users/sghoweri/orgs",
    "repos_url": "https://api.github.com/users/sghoweri/repos",
    "events_url": "https://api.github.com/users/sghoweri/events{/privacy}",
    "received_events_url": "https://api.github.com/users/sghoweri/received_events",
    "type": "User",
    "site_admin": false
  }
}
